neatcode/__init__.py
neatcode/base.py
neatcode/context_management.py
neatcode/decoration.py
neatcode/object_manipulation.py
neatcode/legacy/__init__.py
neatcode/legacy/neatcode.py
neatcode/policy/__init__.py
neatcode/policy/argument_substitution.py
neatcode_txetx-0.0.3.dist-info/LICENSE
neatcode_txetx-0.0.3.dist-info/METADATA
neatcode_txetx-0.0.3.dist-info/WHEEL
neatcode_txetx-0.0.3.dist-info/top_level.txt
neatcode_txetx-0.0.3.dist-info/RECORD
