Metadata-Version: 2.1
Name: neatcode-txetx
Version: 0.0.3
Summary: A small pure python library containing implementations of common python patterns
Home-page: https://github.com/txetxedeletxe/neatcode
Author: Edu Vallejo Arguinzoniz
Author-email: vallezoniz@gmail.com
License: UNKNOWN
Project-URL: Bug Tracker, https://github.com/txetxedeletxe/neatcode/issues
Platform: UNKNOWN
Classifier: Programming Language :: Python :: 3
Classifier: License :: OSI Approved :: GNU General Public License v3 (GPLv3)
Classifier: Operating System :: OS Independent
Requires-Python: >=3.6
License-File: LICENSE
